{
  "suggest.autoTrigger": "",
  "eslint.nodePath": "/home/za/.nvm/versions/node/v24.1.0/bin/node",

  "eslint.enable": true,
  "eslint.packageManager": "npm",

  "eslint.experimental": { "useFlatConfig": true },
  "eslint.options": { "overrideConfigFile": "/home/za/eslint.config.js" },

  "eslint.probe": [
    "javascript",
    "javascriptreact",
    "typescript",
    "typescriptreact"
  ],

  "tsserver.enable": true,
  "tsserver.formatOnType": true,
  "tsserver.log": "verbose",
  "suggest.autoTrigger": "none",
  "deno.enable": true,
  "deno.import_map": "./import_map.json",
  "html.deno.import_map": "./import_map.json",
  "editor.codeActionsOnSave": {
    "source.fixAll.eslint": true
  }
}
